{  "schema": "btc_pulse_score_history/1.0",  "entries": [   {    "ts": 1782673208.4726756,    "utc": "2026-06-28 19:00:08 UTC",    "ticks": 1,    "settled": 0,    "scores": {     "trading_performance": 52.5,     "operation": 82.0,     "external_signals": 37.0,     "overall": 56.0,     "grades": {      "trading_performance": "F",      "operation": "B",      "external_signals": "F",      "overall": "F"     }    }   },   {    "ts": 1782673465.453017,    "utc": "2026-06-28 19:04:25 UTC",    "ticks": 18,    "settled": 0,    "scores": {     "trading_performance": 52.5,     "operation": 67.1,     "external_signals": 37.0,     "overall": 52.3,     "grades": {      "trading_performance": "F",      "operation": "D",      "external_signals": "F",      "overall": "F"     }    }   },   {    "ts": 1782674110.43904,    "utc": "2026-06-28 19:15:10 UTC",    "ticks": 61,    "settled": 0,    "scores": {     "trading_performance": 55.0,     "operation": 67.2,     "external_signals": 37.0,     "overall": 53.5,     "grades": {      "trading_performance": "F",      "operation": "D",      "external_signals": "F",      "overall": "F"     }    }   },   {    "ts": 1782675010.3473074,    "utc": "2026-06-28 19:30:10 UTC",    "ticks": 121,    "settled": 0,    "scores": {     "trading_performance": 55.0,     "operation": 67.4,     "external_signals": 41.9,     "overall": 54.8,     "grades": {      "trading_performance": "F",      "operation": "D",      "external_signals": "F",      "overall": "F"     }    }   },   {    "ts": 1782676810.7911875,    "utc": "2026-06-28 20:00:10 UTC",    "ticks": 241,    "settled": 0,    "scores": {     "trading_performance": 55.1,     "operation": 67.7,     "external_signals": 41.9,     "overall": 55.0,     "grades": {      "trading_performance": "F",      "operation": "D",      "external_signals": "F",      "overall": "F"     }    }   },   {    "ts": 1782678625.3498719,    "utc": "2026-06-28 20:30:25 UTC",    "ticks": 362,    "settled": 0,    "scores": {     "trading_performance": 55.3,     "operation": 68.1,     "external_signals": 41.9,     "overall": 55.1,     "grades": {      "trading_performance": "F",      "operation": "D",      "external_signals": "F",      "overall": "F"     }    }   },   {    "ts": 1782679507.4481962,    "utc": "2026-06-28 20:45:07 UTC",    "ticks": 45,    "settled": 0,    "scores": {     "trading_performance": 55.7,     "operation": 68.3,     "external_signals": 31.2,     "overall": 52.7,     "grades": {      "trading_performance": "F",      "operation": "D",      "external_signals": "F",      "overall": "F"     }    }   },   {    "ts": 1782681307.4649093,    "utc": "2026-06-28 21:15:07 UTC",    "ticks": 165,    "settled": 0,    "scores": {     "trading_performance": 55.7,     "operation": 68.6,     "external_signals": 32.1,     "overall": 53.0,     "grades": {      "trading_performance": "F",      "operation": "D",      "external_signals": "F",      "overall": "F"     }    }   },   {    "ts": 1782682204.004552,    "utc": "2026-06-28 21:30:04 UTC",    "ticks": 14,    "settled": 0,    "scores": {     "trading_performance": 55.8,     "operation": 68.8,     "external_signals": 36.2,     "overall": 54.1,     "grades": {      "trading_performance": "F",      "operation": "D",      "external_signals": "F",      "overall": "F"     }    }   },   {    "ts": 1782684010.8041177,    "utc": "2026-06-28 22:00:10 UTC",    "ticks": 91,    "settled": 0,    "scores": {     "trading_performance": 57.1,     "operation": 69.2,     "external_signals": 37.1,     "overall": 55.1,     "grades": {      "trading_performance": "F",      "operation": "D",      "external_signals": "F",      "overall": "F"     }    }   },   {    "ts": 1782684910.8010511,    "utc": "2026-06-28 22:15:10 UTC",    "ticks": 151,    "settled": 0,    "scores": {     "trading_performance": 58.9,     "operation": 69.3,     "external_signals": 37.3,     "overall": 56.1,     "grades": {      "trading_performance": "F",      "operation": "D",      "external_signals": "F",      "overall": "F"     }    }   },   {    "ts": 1782684970.738261,    "utc": "2026-06-28 22:16:10 UTC",    "ticks": 155,    "settled": 0,    "scores": {     "trading_performance": 58.9,     "operation": 69.4,     "external_signals": 49.4,     "overall": 59.1,     "grades": {      "trading_performance": "F",      "operation": "D",      "external_signals": "F",      "overall": "F"     }    }   },   {    "ts": 1782686785.7063463,    "utc": "2026-06-28 22:46:25 UTC",    "ticks": 276,    "settled": 0,    "scores": {     "trading_performance": 60.3,     "operation": 69.7,     "external_signals": 49.4,     "overall": 59.9,     "grades": {      "trading_performance": "D",      "operation": "D",      "external_signals": "F",      "overall": "F"     }    }   },   {    "ts": 1782688510.7215822,    "utc": "2026-06-28 23:15:10 UTC",    "ticks": 391,    "settled": 0,    "scores": {     "trading_performance": 63.1,     "operation": 70.1,     "external_signals": 49.4,     "overall": 61.4,     "grades": {      "trading_performance": "D",      "operation": "C",      "external_signals": "F",      "overall": "D"     }    }   },   {    "ts": 1782690311.0026531,    "utc": "2026-06-28 23:45:11 UTC",    "ticks": 511,    "settled": 0,    "scores": {     "trading_performance": 64.3,     "operation": 70.4,     "external_signals": 49.4,     "overall": 62.1,     "grades": {      "trading_performance": "D",      "operation": "C",      "external_signals": "F",      "overall": "D"     }    }   },   {    "ts": 1782692110.7020411,    "utc": "2026-06-29 00:15:10 UTC",    "ticks": 631,    "settled": 0,    "scores": {     "trading_performance": 66.4,     "operation": 70.8,     "external_signals": 49.4,     "overall": 63.3,     "grades": {      "trading_performance": "D",      "operation": "C",      "external_signals": "F",      "overall": "D"     }    }   }  ] }